README.md
setup.py
musicAlgLib/__init__.py
musicAlgLib/commFunction.py
musicAlgLib/main.py
musicAlgLib.egg-info/PKG-INFO
musicAlgLib.egg-info/SOURCES.txt
musicAlgLib.egg-info/dependency_links.txt
musicAlgLib.egg-info/requires.txt
musicAlgLib.egg-info/top_level.txt
musicAlgLib/AGC_EVALUATION/CAL_MUSIC_STABILITY.py
musicAlgLib/AGC_EVALUATION/__init__.py
musicAlgLib/CLIPPING_DETECTION/__init__.py
musicAlgLib/CLIPPING_DETECTION/audio_clip_detection.py
musicAlgLib/DLLS/cygwin1.dll
musicAlgLib/DLLS/matchsig.dll
musicAlgLib/DLLS/matchsig.dylib
musicAlgLib/DLLS/matchsig.so
musicAlgLib/DLLS/musicStability.dll
musicAlgLib/DLLS/musicStability.dylib
musicAlgLib/DLLS/musicStability.so
musicAlgLib/DLLS/pcc.dll
musicAlgLib/DLLS/pcc.dylib
musicAlgLib/DLLS/pcc.so
musicAlgLib/DLLS/peaqb
musicAlgLib/DLLS/peaqb.exe
musicAlgLib/DLLS/silero_vad.jit
musicAlgLib/DLLS/snr_music.dll
musicAlgLib/DLLS/snr_music.dylib
musicAlgLib/DLLS/snr_music.so
musicAlgLib/DLLs/__init__.py
musicAlgLib/DynmicRange/__init__.py
musicAlgLib/FUNCTION/__init__.py
musicAlgLib/FUNCTION/audioFunction.py
musicAlgLib/FrequencyResponse/__init__.py
musicAlgLib/Noise_Suppression/__init__.py
musicAlgLib/Noise_Suppression/noiseFuction.py
musicAlgLib/PCC/Pearson_CC.py
musicAlgLib/PCC/__init__.py
musicAlgLib/PEAQ/PEAQ.py
musicAlgLib/PEAQ/__init__.py
musicAlgLib/PESQ/PESQ.py
musicAlgLib/PESQ/__init__.py
musicAlgLib/PLAY_DELAY/__init__.py
musicAlgLib/POLQA/POLQA.py
musicAlgLib/POLQA/__init__.py
musicAlgLib/POLQA/file_server.py
musicAlgLib/POLQA/polqa_client.py
musicAlgLib/POLQA/polqa_server.py
musicAlgLib/POLQA/socketClient.py
musicAlgLib/SNR_ESTIMATION/MATCH_SIG.py
musicAlgLib/SNR_ESTIMATION/SNR_MUSIC.py
musicAlgLib/SNR_ESTIMATION/__init__.py
musicAlgLib/STI/__init__.py
musicAlgLib/STI/cal_sti.py
musicAlgLib/STI/sti.py
musicAlgLib/VAD_NN/__init__.py
musicAlgLib/VAD_NN/hubconf.py
musicAlgLib/VISQOL/__init__.py
musicAlgLib/computeAudioQuality/__init__.py
musicAlgLib/computeAudioQuality/mainProcess.py
musicAlgLib/formatConvert/__init__.py
musicAlgLib/formatConvert/wav_pcm.py
musicAlgLib/resample/__init__.py
musicAlgLib/resample/resampler.py
musicAlgLib/tests/__init__.py
