Metadata-Version: 2.1
Name: musicAlgLib
Version: 1.1.8
Summary: audio algorithms to compute and test music quality
Home-page: https://github.com/pypa/sampleproject
Author:  MA JIANLI
Author-email: majianli@corp.netease.com
License: MIT
Platform: UNKNOWN
Classifier: Programming Language :: Python :: 3
Classifier: License :: OSI Approved :: MIT License
Classifier: Operating System :: OS Independent
Requires-Python: >=3.6
